asyncwrap.py
asyncwrap-0.1.0.dist-info/DESCRIPTION.rst
asyncwrap-0.1.0.dist-info/METADATA
asyncwrap-0.1.0.dist-info/RECORD
asyncwrap-0.1.0.dist-info/WHEEL
asyncwrap-0.1.0.dist-info/metadata.json
asyncwrap-0.1.0.dist-info/top_level.txt
