Metadata-Version: 2.0
Name: asyncwrap
Version: 0.1.0
Summary: Simple asynchronous wrappers for synchronous blocking code
Home-page: https://github.com/mtasic85/asyncwrap
Author: Marko Tasic
Author-email: mtasic85@gmail.com
License: MIT
Keywords: async asyncio wrapper high-level
Platform: UNKNOWN
Classifier: Development Status :: 3 - Alpha
Classifier: Intended Audience :: Developers
Classifier: Topic :: Software Development
Classifier: License :: OSI Approved :: MIT License
Classifier: Programming Language :: Python :: 3.5
